{
 "keyword": "ニチホ",
 "updated": "2026-06-26 11:56 UTC",
 "posts": [
  {
   "a": "@kogemayo",
   "t": "RT @Yamachirounebi: まぁ、百田ニチホより参政党の方がみんなから右認識があるようなものだと思ってるけど…",
   "d": "2026-06-26 10:51",
   "c": "neg"
  },
  {
   "a": "@QIIE8ROYeGO7HJT",
   "t": "@kitamuraharuo 常識を学ぼうとしない\nニチホ党首　エコチェンなかで\nご満悦🤣",
   "d": "2026-06-26 10:55",
   "c": "neg"
  },
  {
   "a": "@Nihon_Gimon",
   "t": "@BQgCq4FjTk775 ほんとニチホのアホさ加減には敵いませんて😌",
   "d": "2026-06-26 10:59",
   "c": "neg"
  },
  {
   "a": "@akinemo2",
   "t": "RT @6503thcssGi5: 反日保・反守る会の人達はひたすら飯山さんを叩いているけれど、それをすれば日本保守党へ利敵行為していることになり、守る会を潰せばニチホは生き残るだけなんだが。何を思い違いして叩き続けてるのかわからない。\n守る会は保守党が訴訟取り下げて党を畳めば…",
   "d": "2026-06-26 11:05",
   "c": "neg"
  },
  {
   "a": "@akinemo2",
   "t": "RT @8fQewiRAuZ34721: 【キクタケ】！！\nキクタケと他10人のニチホ信者が、\n飯山さんより３00万円の内容証明書が\n届く😁\n２週間以内に示談に応じなければ更に\n金額を上乗せした金額を裁判にて決着。\n\nキクタケ氏焦る焦る焦る😁\n\n飯山から皆んなを守る会を発足🤪",
   "d": "2026-06-26 11:11",
   "c": "bad"
  },
  {
   "a": "@5AwsEisv0dQvxfz",
   "t": "RT @snake1gou: 選挙中はゲイの「ゲ」の字も出さなかったのに、当選してから後出し恥ずかしいニチホとめいろまw https://t.co/DCF4QfwNl7",
   "d": "2026-06-26 11:12",
   "c": "neg"
  },
  {
   "a": "@haru32240750282",
   "t": "@i4CXbFKvwRUpJs0 斎藤支持者みたいやし...\nあとニチホもいてますね笑",
   "d": "2026-06-26 11:35",
   "c": "neg"
  },
  {
   "a": "@isacchin",
   "t": "百田は自分が仕掛けた訴訟で全部負けてる上に、刑事告訴されて負けたら赤っ恥だね。。\n\n竹上氏は勝ち目があるから告訴したんだろうけど、それが普通だよね。。\n\nなんでニチホは勝ち目の無い訴訟なんかして、無駄に金を使ってるんだろう。。\n\n元は党員のカネだから、自分は痛くもかゆくもないのかね。。 https://t.co/uunlCC5W4L",
   "d": "2026-06-26 11:36",
   "c": "neg"
  },
  {
   "a": "@Bn2Ukqcpt643250",
   "t": "@UopX54i54C4671 修司の娘です🙇\n父も竹上さんを応援したい❗と言ってます\n\n只、飯山さんと１度連絡を取って欲しい❗\nと、言ってます。竹上さんがまだニチホの\n所属だった頃、百や有が飯山さんに対し\n誹謗中傷してた事は知っていたはず❗\nその時に声を上げて欲しかったと…\n\nあの時の立場は分かりますが…🙇",
   "d": "2026-06-26 11:51",
   "c": "neg"
  },
  {
   "a": "@RWuNs7FWgI5TJkO",
   "t": "RT @taku1097389: ニチホについて「ほしゅくん」語る・の巻 https://t.co/mFncxTBOpv @YouTubeより \nhttps://t.co/mFncxTBOpv",
   "d": "2026-06-26 11:54",
   "c": "normal"
  },
  {
   "a": "@FACXJGYcsv28103",
   "t": "RT @8fQewiRAuZ34721: 【キクタケ】！！\nキクタケと他10人のニチホ信者が、\n飯山さんより３00万円の内容証明書が\n届く😁\n２週間以内に示談に応じなければ更に\n金額を上乗せした金額を裁判にて決着。\n\nキクタケ氏焦る焦る焦る😁\n\n飯山から皆んなを守る会を発足🤪",
   "d": "2026-06-25 22:11",
   "c": "bad"
  },
  {
   "a": "@QIIE8ROYeGO7HJT",
   "t": "@kitamuraharuo ダメ？\nソリャ　ニチホでしょ",
   "d": "2026-06-25 22:31",
   "c": "neg"
  },
  {
   "a": "@uqcDAqDMV643951",
   "t": "RT @snake1gou: 選挙中はゲイの「ゲ」の字も出さなかったのに、当選してから後出し恥ずかしいニチホとめいろまw https://t.co/DCF4QfwNl7",
   "d": "2026-06-25 22:35",
   "c": "neg"
  },
  {
   "a": "@maji_5263",
   "t": "福永活也さんって、訴訟手続が早いだけで、完全敗訴請け負い弁護士🤔ニチホは無能な人ばかり巻き取ってるの？www",
   "d": "2026-06-25 22:42",
   "c": "neg"
  },
  {
   "a": "@mejirotoume12",
   "t": "RT @mofvmofu: 俺、相手が玉木だろうが立憲議員だろうが参政党ニチホだろうがデマで貶める事は絶対に容認しないのよ。\n\nこれまで自民応援してきたけど、歴代総理や議員は現在進行形でデマを撒かれてるし当時のデマのレッテル貼られたまま。…",
   "d": "2026-06-25 23:01",
   "c": "pos"
  },
  {
   "a": "@QBK_longride",
   "t": "RT @septuagintasome: 夜鷹が被ってるのは手拭いだよ。ヒジャブはどちらかと言えば頭巾だろ。参政党とニチホを応援して保守気取るなら、そのぐらいは知っておけよ。 https://t.co/VGRuD78Zyn",
   "d": "2026-06-25 23:14",
   "c": "neg"
  },
  {
   "a": "@itsurotti",
   "t": "それがわかるなら何故ニチホに協力する？\nなぜ知らないことを知ったように吹聴する？ https://t.co/RfyDrC8D1u",
   "d": "2026-06-25 23:47",
   "c": "neg"
  },
  {
   "a": "@haru32240750282",
   "t": "@i4CXbFKvwRUpJs0 ニチホと同レベル笑",
   "d": "2026-06-26 00:00",
   "c": "neg"
  },
  {
   "a": "@akinemo2",
   "t": "RT @GOKICHAN_IQ3: ネトウヨ大戦は近藤さんの勝ちか。\nそういえば闇クマ戦でもニチホは負けてたよね。\n支持者の頭の悪い爺さん達は総じてボケてるからスルーするんだろうね。",
   "d": "2026-06-26 00:02",
   "c": "bad"
  },
  {
   "a": "@akan1y",
   "t": "RT @snake1gou: 選挙中はゲイの「ゲ」の字も出さなかったのに、当選してから後出し恥ずかしいニチホとめいろまw https://t.co/DCF4QfwNl7",
   "d": "2026-06-26 00:20",
   "c": "neg"
  },
  {
   "a": "@BB_Nackey",
   "t": "その通りです、とにかく叩くネタ探し。\n最たる例が、例の学会教授との論争における 博士の切り抜き。教授発信分 は知らん顔、ニチホとの争いにもそれを根拠に…。保守論客でさえ、党を批判しながら、博士をチラッと。\n私はいつも言う。\n専門家の論争に、素人が 軽々に絡むんじゃないと‼️ https://t.co/R1fIrX3VGI",
   "d": "2026-06-25 15:24",
   "c": "neg"
  },
  {
   "a": "@KZDeh68055",
   "t": "RT @snake1gou: 選挙中はゲイの「ゲ」の字も出さなかったのに、当選してから後出し恥ずかしいニチホとめいろまw https://t.co/DCF4QfwNl7",
   "d": "2026-06-25 15:28",
   "c": "neg"
  },
  {
   "a": "@pqQISYRTbj8S02c",
   "t": "@IsamuArchitect @nihonpatriot 参政ニチホは🏺だよ\nどんな法案に賛成してるか\n調べたら自民党の補完勢力とわかるよ",
   "d": "2026-06-25 15:36",
   "c": "neg"
  },
  {
   "a": "@t4gvLK1dH253dXI",
   "t": "🤣マナーもニチホ品質🤣 https://t.co/Jj8lokVRcr",
   "d": "2026-06-25 15:49",
   "c": "neg"
  },
  {
   "a": "@AkiTak14",
   "t": "@IiyamaAkari あれ田中けん氏というと元ニチ党所属議員の方でしたっけ‥何をおっしゃっているのか‥ニチホの幻想から覚めてもまだ全てがよく理解されるわけではないということですね‥人は間違える‥せめて事実は間違えないように捉えたいものです‥",
   "d": "2026-06-25 16:00",
   "c": "normal"
  },
  {
   "a": "@qu318810",
   "t": "@aki20240628 こんな国政政党あって良いのか！\nニチホに愛はないニダかー！",
   "d": "2026-06-25 16:40",
   "c": "neg"
  },
  {
   "a": "@6NYZP5Q2Wz33348",
   "t": "言ってない事を誤読しミスリードを広げて正論を展開し自己正当化する\nしかもブロックし反論できない状態で\nもちろん正論なのでFFさんからは賛同を得られて満足だろうがそもそも論点違う\n\nこれさワイが大っ嫌いなニチホ界隈と同じやり方なんよ\nそれをまぁまぁ中垢の参政支持者がしちゃうのねガッカリ",
   "d": "2026-06-25 17:19",
   "c": "neg"
  },
  {
   "a": "@majinpower_love",
   "t": "@oshirasepost 金で解決するんじゃダメなんよ\n\n泣き叫ぶニチホが収監されなきゃ。\nそして信者も後追い◯◯…\n\n掃除ね🧹",
   "d": "2026-06-25 17:22",
   "c": "bad"
  },
  {
   "a": "@zr04NzpB8pYOZ44",
   "t": "RT @AkiTak14: @IiyamaAkari あれ田中けん氏というと元ニチ党所属議員の方でしたっけ‥何をおっしゃっているのか‥ニチホの幻想から覚めてもまだ全てがよく理解されるわけではないということですね‥人は間違える‥せめて事実は間違えないように捉えたいものです‥",
   "d": "2026-06-25 17:41",
   "c": "normal"
  },
  {
   "a": "@Air_Lights1214",
   "t": "RT @snake1gou: 選挙中はゲイの「ゲ」の字も出さなかったのに、当選してから後出し恥ずかしいニチホとめいろまw https://t.co/DCF4QfwNl7",
   "d": "2026-06-25 18:03",
   "c": "neg"
  },
  {
   "a": "@Horie84473166",
   "t": "RT @IiyamaAkari: このあと１７：１５からライブ配信します。\n【高市支持上昇69%！いさ進一「質問したいならニコ生有料会員になれ」守銭奴&amp;ニチホ化！】首相専用車トヨタ最高級SUV！野党週刊誌片手に高市追求？！ https://t.co/E2Berx9bWp @Yo…",
   "d": "2026-06-25 09:37",
   "c": "neg"
  },
  {
   "a": "@tsk_2017",
   "t": "これもニチホ敗訴か。他と比べて分が悪いと個人的には見てたが、名誉毀損認められなくてよかった https://t.co/VzV1YBFX7d",
   "d": "2026-06-25 09:43",
   "c": "normal"
  },
  {
   "a": "@snake1gou",
   "t": "@div86621833 ついに北村氏も愛想つきましたかねｗニチホにｗ",
   "d": "2026-06-25 09:47",
   "c": "neg"
  },
  {
   "a": "@rcTo0BfysX6234",
   "t": "@p2uuFKO110G3iKg ニチホは解散するね😂\n北村は高市応援団だから！",
   "d": "2026-06-25 09:57",
   "c": "neg"
  },
  {
   "a": "@6503thcssGi5",
   "t": "@Tsukinowaguma5 @tK0MmT05v4s666 ニチホの歌謡曲",
   "d": "2026-06-25 10:05",
   "c": "normal"
  },
  {
   "a": "@kouhaku385",
   "t": "RT @mofvmofu: 俺、今の自民支持層(主に高市支持層)をデカいニチホってよく言うんだけど、\n\nそれを今可視化してるのが西田さん(リハックに出てるよー)の件。\n\n文春報道で伊佐議員が総理に詰める\n\n→支持層が群れをなして伊佐議員に詰め寄る\n→そのうちの1人が政治資金の領…",
   "d": "2026-06-25 10:06",
   "c": "neg"
  },
  {
   "a": "@11090618",
   "t": "@kitamuraharuo @yonoi_yuka ニチホって似たようなもんでは？\n百田何某は保守ビジネスですもんね。\n反高市の。",
   "d": "2026-06-25 10:08",
   "c": "neg"
  },
  {
   "a": "@Gocce_di_vento",
   "t": "RT @mofvmofu: 俺、相手が玉木だろうが立憲議員だろうが参政党ニチホだろうがデマで貶める事は絶対に容認しないのよ。\n\nこれまで自民応援してきたけど、歴代総理や議員は現在進行形でデマを撒かれてるし当時のデマのレッテル貼られたまま。…",
   "d": "2026-06-25 10:14",
   "c": "pos"
  },
  {
   "a": "@1779keiji",
   "t": "@div86621833 近づいた人は必ず離れていくのがニチホ標準。\n🤣🤣🤣",
   "d": "2026-06-25 10:15",
   "c": "neg"
  },
  {
   "a": "@takuru0100",
   "t": "@0211jaguar ニチホがこの2人だけのものであることを再確認させられる絵面\n\nおそらく北村は既に切られてるな🤔",
   "d": "2026-06-25 10:20",
   "c": "neg"
  },
  {
   "a": "@mukotokacha0220",
   "t": "RT @mofvmofu: 俺、今の自民支持層(主に高市支持層)をデカいニチホってよく言うんだけど、\n\nそれを今可視化してるのが西田さん(リハックに出てるよー)の件。\n\n文春報道で伊佐議員が総理に詰める\n\n→支持層が群れをなして伊佐議員に詰め寄る\n→そのうちの1人が政治資金の領…",
   "d": "2026-06-24 23:29",
   "c": "neg"
  },
  {
   "a": "@purintaso_ham",
   "t": "RT @mofvmofu: 俺、今の自民支持層(主に高市支持層)をデカいニチホってよく言うんだけど、\n\nそれを今可視化してるのが西田さん(リハックに出てるよー)の件。\n\n文春報道で伊佐議員が総理に詰める\n\n→支持層が群れをなして伊佐議員に詰め寄る\n→そのうちの1人が政治資金の領…",
   "d": "2026-06-24 23:32",
   "c": "neg"
  },
  {
   "a": "@urawanonyanko",
   "t": "RT @mofvmofu: 俺、相手が玉木だろうが立憲議員だろうが参政党ニチホだろうがデマで貶める事は絶対に容認しないのよ。\n\nこれまで自民応援してきたけど、歴代総理や議員は現在進行形でデマを撒かれてるし当時のデマのレッテル貼られたまま。…",
   "d": "2026-06-24 23:35",
   "c": "pos"
  },
  {
   "a": "@doteramon",
   "t": "RT @mofvmofu: 俺、相手が玉木だろうが立憲議員だろうが参政党ニチホだろうがデマで貶める事は絶対に容認しないのよ。\n\nこれまで自民応援してきたけど、歴代総理や議員は現在進行形でデマを撒かれてるし当時のデマのレッテル貼られたまま。…",
   "d": "2026-06-24 23:42",
   "c": "pos"
  },
  {
   "a": "@akan1y",
   "t": "マルチ北村\n\nニチホを腐してますね。　笑 https://t.co/TIymdpqUV3",
   "d": "2026-06-24 23:43",
   "c": "neg"
  },
  {
   "a": "@PmEt70u1rBrJUZU",
   "t": "RT @mofvmofu: 俺、今の自民支持層(主に高市支持層)をデカいニチホってよく言うんだけど、\n\nそれを今可視化してるのが西田さん(リハックに出てるよー)の件。\n\n文春報道で伊佐議員が総理に詰める\n\n→支持層が群れをなして伊佐議員に詰め寄る\n→そのうちの1人が政治資金の領…",
   "d": "2026-06-24 23:44",
   "c": "neg"
  },
  {
   "a": "@Cheers_TokyoJPN",
   "t": "RT @mofvmofu: 俺、今の自民支持層(主に高市支持層)をデカいニチホってよく言うんだけど、\n\nそれを今可視化してるのが西田さん(リハックに出てるよー)の件。\n\n文春報道で伊佐議員が総理に詰める\n\n→支持層が群れをなして伊佐議員に詰め寄る\n→そのうちの1人が政治資金の領…",
   "d": "2026-06-24 23:44",
   "c": "neg"
  },
  {
   "a": "@x91K6ghSUoWCByv",
   "t": "RT @mofvmofu: 俺、相手が玉木だろうが立憲議員だろうが参政党ニチホだろうがデマで貶める事は絶対に容認しないのよ。\n\nこれまで自民応援してきたけど、歴代総理や議員は現在進行形でデマを撒かれてるし当時のデマのレッテル貼られたまま。…",
   "d": "2026-06-24 23:49",
   "c": "pos"
  },
  {
   "a": "@okane_plus",
   "t": "RT @mofvmofu: 俺、今の自民支持層(主に高市支持層)をデカいニチホってよく言うんだけど、\n\nそれを今可視化してるのが西田さん(リハックに出てるよー)の件。\n\n文春報道で伊佐議員が総理に詰める\n\n→支持層が群れをなして伊佐議員に詰め寄る\n→そのうちの1人が政治資金の領…",
   "d": "2026-06-24 23:49",
   "c": "neg"
  },
  {
   "a": "@nM___0606___",
   "t": "RT @mofvmofu: 俺、相手が玉木だろうが立憲議員だろうが参政党ニチホだろうがデマで貶める事は絶対に容認しないのよ。\n\nこれまで自民応援してきたけど、歴代総理や議員は現在進行形でデマを撒かれてるし当時のデマのレッテル貼られたまま。…",
   "d": "2026-06-24 23:51",
   "c": "pos"
  }
 ]
}